Workbook

Sheet Read Me
A1: Chapter 8: Irrecoverable Debts and Allowance for Receivables
A2: Senior 1 Accounting. Free to use and share.
B4: How to use this workbook
B5: 1. Start with the worked example sheets. Change any blue number and watch every answer update.
B6: 2. Then try the Practice sheet. Type your answers in the yellow cells.
B7: 3. The Check column tells you 'Correct' or 'Try again' as soon as you type.
B8: 4. The Answers sheet is hidden. When you finish, right-click any sheet tab and choose Unhide to see full answers.
B10: Colour key
B11: Blue text = an input you can change.
B12: Black text = a formula. Do not type over it.
B13: Yellow cell = your answer goes here.

Sheet Allowance Calculator
A1: Worked example 8.3: allowance for irrecoverable debts
A2: Change the blue numbers. Everything else recalculates.
A4: Item | B4: 2023 | C4: 2024 | D4: 2025
A5: Trade receivables before write-offs | B5: 20500 | C5: 26800 | D5: 18600
A6: Less: irrecoverable debts written off | B6: 500 | C6: 800 | D6: 600
A7: Trade receivables after write-offs | B7: =B5-B6 -> 20000 | C7: =C5-C6 -> 26000 | D7: =D5-D6 -> 18000
A8: Allowance rate | B8: 0.05 | C8: 0.05 | D8: 0.05
A9: Allowance required at year end (step 1) | B9: =ROUND(B7*B8,2) -> 1000 | C9: =ROUND(C7*C8,2) -> 1300 | D9: =ROUND(D7*D8,2) -> 900
A10: Less: allowance brought forward | B10: 0 | C10: =B9 -> 1000 | D10: =C9 -> 1300
A11: Change in allowance (step 2) | B11: =B9-B10 -> 1000 | C11: =C9-C10 -> 300 | D11: =D9-D10 -> -400
A12: Treatment in Statement of Profit or Loss (step 3) | B12: =IF(B11>0,"Expense (increase)",IF(B11<0,"Income (decrease)","No entry")) -> Expense (increase) | C12: =IF(C11>0,"Expense (increase)",IF(C11<0,"Income (decrease)","No entry")) -> Expense (increase) | D12: =IF(D11>0,"Expense (increase)",IF(D11<0,"Income (decrease)","No entry")) -> Income (decrease)
A13: Amount to Statement of Profit or Loss | B13: =ABS(B11) -> 1000 | C13: =ABS(C11) -> 300 | D13: =ABS(D11) -> 400
A14: Statement of Financial Position extract
A15: Trade receivables | B15: =B7 -> 20000 | C15: =C7 -> 26000 | D15: =D7 -> 18000
A16: Less: allowance for irrecoverable debts | B16: =B9 -> 1000 | C16: =C9 -> 1300 | D16: =D9 -> 900
A17: Net trade receivables (current asset) | B17: =B15-B16 -> 19000 | C17: =C15-C16 -> 24700 | D17: =D15-D16 -> 17100
A18: Statement of Profit or Loss extract
A19: Irrecoverable debts written off (expense) | B19: =B6 -> 500 | C19: =C6 -> 800 | D19: =D6 -> 600
A21: Rule: only the CHANGE in the allowance goes to the Statement of Profit or Loss.
A22: Blue = input. The 2023 opening allowance is 0 because the allowance is created in 2023.

Sheet Allowance Ledger
A1: Allowance for irrecoverable debts account
A2: Built from the Allowance Calculator sheet. Amounts of 0 show as a dash.
A4: Year ended 31 December 2023
A5: Dr | B5: Details | C5: $ | E5: Cr | F5: Details | G5: $
A6: Dec 31 | B6: Income statement (decrease) | C6: =IF('Allowance Calculator'!B11<0,-'Allowance Calculator'!B11,0) -> 0 | E6: Jan 1 | F6: Balance b/d | G6: ='Allowance Calculator'!B10 -> 0
A7: Dec 31 | B7: Balance c/d | C7: ='Allowance Calculator'!B9 -> 1000 | E7: Dec 31 | F7: Income statement (increase) | G7: =IF('Allowance Calculator'!B11>0,'Allowance Calculator'!B11,0) -> 1000
C8: =C6+C7 -> 1000 | G8: =G6+G7 -> 1000
E9: Jan 1 | F9: Balance b/d (next year) | G9: ='Allowance Calculator'!B9 -> 1000
A11: Year ended 31 December 2024
A12: Dr | B12: Details | C12: $ | E12: Cr | F12: Details | G12: $
A13: Dec 31 | B13: Income statement (decrease) | C13: =IF('Allowance Calculator'!C11<0,-'Allowance Calculator'!C11,0) -> 0 | E13: Jan 1 | F13: Balance b/d | G13: ='Allowance Calculator'!C10 -> 1000
A14: Dec 31 | B14: Balance c/d | C14: ='Allowance Calculator'!C9 -> 1300 | E14: Dec 31 | F14: Income statement (increase) | G14: =IF('Allowance Calculator'!C11>0,'Allowance Calculator'!C11,0) -> 300
C15: =C13+C14 -> 1300 | G15: =G13+G14 -> 1300
E16: Jan 1 | F16: Balance b/d (next year) | G16: ='Allowance Calculator'!C9 -> 1300
A18: Year ended 31 December 2025
A19: Dr | B19: Details | C19: $ | E19: Cr | F19: Details | G19: $
A20: Dec 31 | B20: Income statement (decrease) | C20: =IF('Allowance Calculator'!D11<0,-'Allowance Calculator'!D11,0) -> 400 | E20: Jan 1 | F20: Balance b/d | G20: ='Allowance Calculator'!D10 -> 1300
A21: Dec 31 | B21: Balance c/d | C21: ='Allowance Calculator'!D9 -> 900 | E21: Dec 31 | F21: Income statement (increase) | G21: =IF('Allowance Calculator'!D11>0,'Allowance Calculator'!D11,0) -> 0
C22: =C20+C21 -> 1300 | G22: =G20+G21 -> 1300
E23: Jan 1 | F23: Balance b/d (next year) | G23: ='Allowance Calculator'!D9 -> 900

Sheet Practice
A1: Practice: Model Question 8.11 (Grace)
A2: Type your answers in the yellow cells. The Check column marks them.
A3: Grace keeps an allowance for irrecoverable debts. Year end 31 December.
A5: Data (from Model Question 8.11) | B5: 2023 | C5: 2024 | D5: 2025
A6: Trade receivables before write-offs | B6: 40000 | C6: 50000 | D6: 36000
A7: Debts to be written off | B7: 0 | C7: 0 | D7: 1000
A8: Allowance rate | B8: 0.03 | C8: 0.03 | D8: 0.03
A9: There was no allowance before 2023.
A11: Question | B11: Your answer | C11: Check
A12: Part a) Allowance required
A13: Allowance required at 31 December 2023 | C13: =IF(B13="","",IFERROR(IF(ABS(B13-Answers!B13)<0.5,"Correct","Try again"),"Enter a number"))
A14: Allowance required at 31 December 2024 | C14: =IF(B14="","",IFERROR(IF(ABS(B14-Answers!B14)<0.5,"Correct","Try again"),"Enter a number"))
A15: Allowance required at 31 December 2025 | C15: =IF(B15="","",IFERROR(IF(ABS(B15-Answers!B15)<0.5,"Correct","Try again"),"Enter a number"))
A16: Part b) Effect on the Statement of Profit or Loss
A17: Amount to SPL in 2023 (always a positive number) | C17: =IF(B17="","",IFERROR(IF(ABS(B17-Answers!B17)<0.5,"Correct","Try again"),"Enter a number"))
A18: Is 2023 an expense or income? | C18: =IF(B18="","",IF(LOWER(TRIM(B18))=LOWER(Answers!B18),"Correct","Try again"))
A19: Amount to SPL in 2024 (always a positive number) | C19: =IF(B19="","",IFERROR(IF(ABS(B19-Answers!B19)<0.5,"Correct","Try again"),"Enter a number"))
A20: Is 2024 an expense or income? | C20: =IF(B20="","",IF(LOWER(TRIM(B20))=LOWER(Answers!B20),"Correct","Try again"))
A21: Amount to SPL in 2025 (always a positive number) | C21: =IF(B21="","",IFERROR(IF(ABS(B21-Answers!B21)<0.5,"Correct","Try again"),"Enter a number"))
A22: Is 2025 an expense or income? | C22: =IF(B22="","",IF(LOWER(TRIM(B22))=LOWER(Answers!B22),"Correct","Try again"))
A23: Part d) Statement of Financial Position at 31 December 2025
A24: Trade receivables (after write-offs) | C24: =IF(B24="","",IFERROR(IF(ABS(B24-Answers!B24)<0.5,"Correct","Try again"),"Enter a number"))
A25: Net trade receivables after deducting the allowance | C25: =IF(B25="","",IFERROR(IF(ABS(B25-Answers!B25)<0.5,"Correct","Try again"),"Enter a number"))
A27: Your score (number correct) | B27: =COUNTIF(C12:C26,"Correct")&" / "&COUNTA(B12:B26)&" answered" -> 0 / 0 answered

Sheet Answers
A1: Practice: Model Question 8.11 (Grace): Answers
A2: Every answer is a formula linked to the Practice sheet data.
A11: Question | B11: Answer
A12: Part a) Allowance required
A13: Allowance required at 31 December 2023 | B13: =ROUND((Practice!$B$6-Practice!$B$7)*Practice!$B$8,2) -> 1200
A14: Allowance required at 31 December 2024 | B14: =ROUND((Practice!$C$6-Practice!$C$7)*Practice!$C$8,2) -> 1500
A15: Allowance required at 31 December 2025 | B15: =ROUND((Practice!$D$6-Practice!$D$7)*Practice!$D$8,2) -> 1050
A16: Part b) Effect on the Statement of Profit or Loss
A17: Amount to SPL in 2023 (always a positive number) | B17: =ABS(ROUND((Practice!$B$6-Practice!$B$7)*Practice!$B$8,2)) -> 1200
A18: Is 2023 an expense or income? | B18: =IF(ROUND((Practice!$B$6-Practice!$B$7)*Practice!$B$8,2)>=0,"Expense","Income") -> Expense
A19: Amount to SPL in 2024 (always a positive number) | B19: =ABS(ROUND((Practice!$C$6-Practice!$C$7)*Practice!$C$8,2)-ROUND((Practice!$B$6-Practice!$B$7)*Practice!$B$8,2)) -> 300
A20: Is 2024 an expense or income? | B20: =IF(ROUND((Practice!$C$6-Practice!$C$7)*Practice!$C$8,2)-ROUND((Practice!$B$6-Practice!$B$7)*Practice!$B$8,2)>=0,"Expense","Income") -> Expense
A21: Amount to SPL in 2025 (always a positive number) | B21: =ABS(ROUND((Practice!$D$6-Practice!$D$7)*Practice!$D$8,2)-ROUND((Practice!$C$6-Practice!$C$7)*Practice!$C$8,2)) -> 450
A22: Is 2025 an expense or income? | B22: =IF(ROUND((Practice!$D$6-Practice!$D$7)*Practice!$D$8,2)-ROUND((Practice!$C$6-Practice!$C$7)*Practice!$C$8,2)>=0,"Expense","Income") -> Income
A23: Part d) Statement of Financial Position at 31 December 2025
A24: Trade receivables (after write-offs) | B24: =(Practice!$D$6-Practice!$D$7) -> 35000
A25: Net trade receivables after deducting the allowance | B25: =(Practice!$D$6-Practice!$D$7)-ROUND((Practice!$D$6-Practice!$D$7)*Practice!$D$8,2) -> 33950
