Workbook

Sheet Read Me
A1: Chapter 11: Accruals and Prepayments
A2: Senior 1 Accounting. Free to use and share.
B4: How to use this workbook
B5: 1. Start with the worked example sheets. Change any blue number and watch every answer update.
B6: 2. Then try the Practice sheet. Type your answers in the yellow cells.
B7: 3. The Check column tells you 'Correct' or 'Try again' as soon as you type.
B8: 4. The Answers sheet is hidden. When you finish, right-click any sheet tab and choose Unhide to see full answers.
B10: Colour key
B11: Blue text = an input you can change.
B12: Black text = a formula. Do not type over it.
B13: Yellow cell = your answer goes here.

Sheet Expense Calculator
A1: Expense for the year (worked examples 11.1 to 11.3)
A2: Expense = Paid - Opening accrual + Opening prepayment + Closing accrual - Closing prepayment
A4: Expense | B4: Paid in year | C4: Opening accrual (owing) | D4: Opening prepayment | E4: Closing accrual (owing) | F4: Closing prepayment | G4: Expense for SPL | H4: SFP: other payables | I4: SFP: other receivables
A5: Rent | B5: 11000 | C5: 0 | D5: 0 | E5: 1000 | F5: 0 | G5: =B5-C5+D5+E5-F5 -> 12000 | H5: =E5 -> 1000 | I5: =F5 -> 0
A6: Insurance | B6: 3600 | C6: 0 | D6: 0 | E6: 0 | F6: 900 | G6: =B6-C6+D6+E6-F6 -> 2700 | H6: =E6 -> 0 | I6: =F6 -> 900
A7: Electricity | B7: 2500 | C7: 200 | D7: 0 | E7: 300 | F7: 0 | G7: =B7-C7+D7+E7-F7 -> 2600 | H7: =E7 -> 300 | I7: =F7 -> 0
A8: Total | B8: =SUM(B5:B7) -> 17100 | C8: =SUM(C5:C7) -> 200 | D8: =SUM(D5:D7) -> 0 | E8: =SUM(E5:E7) -> 1300 | F8: =SUM(F5:F7) -> 900 | G8: =SUM(G5:G7) -> 17300 | H8: =SUM(H5:H7) -> 1300 | I8: =SUM(I5:I7) -> 900
A10: Accrued expense: ADD to the expense, show as a current liability.
A11: Prepaid expense: SUBTRACT from the expense, show as a current asset.

Sheet Income Calculator
A1: Income for the year (worked examples 11.4 and 11.5)
A2: Income = Received - Opening accrued + Opening in advance + Closing accrued - Closing in advance
A4: Income | B4: Received in year | C4: Opening accrued income (due) | D4: Opening income in advance | E4: Closing accrued income (due) | F4: Closing income in advance | G4: Income for SPL | H4: SFP: other receivables | I4: SFP: other payables
A5: Rent received | B5: 6500 | C5: 0 | D5: 0 | E5: 0 | F5: 500 | G5: =B5-C5+D5+E5-F5 -> 6000 | H5: =E5 -> 0 | I5: =F5 -> 500
A6: Commission received | B6: 1800 | C6: 0 | D6: 0 | E6: 200 | F6: 0 | G6: =B6-C6+D6+E6-F6 -> 2000 | H6: =E6 -> 200 | I6: =F6 -> 0
A8: Accrued income: ADD to income, show as a current asset.
A9: Income in advance: SUBTRACT from income, show as a current liability.

Sheet Time Apportion
A1: Worked example 11.2: splitting a payment by months
A2: Insurance paid in advance
A4: Amount paid | B4: 3600
A5: Number of months the payment covers | B5: 12
A6: Months falling in THIS financial year | B6: 9
A8: Cost per month | B8: =B4/B5 -> 300
A9: Expense for this year (SPL) | B9: =B8*B6 -> 2700
A10: Prepayment carried to next year (current asset) | B10: =B4-B9 -> 900

Sheet Ledger Account
A1: Electricity account (worked example 11.3)
A2: Linked to row 7 of the Expense Calculator. Change the inputs there.
A4: Dr | B4: Details | C4: $ | E4: Cr | F4: Details | G4: $
A5: Jan 1 | B5: Balance b/d (prepaid) | C5: ='Expense Calculator'!D7 -> 0 | E5: Jan 1 | F5: Balance b/d (owing) | G5: ='Expense Calculator'!C7 -> 200
B6: Bank (paid during year) | C6: ='Expense Calculator'!B7 -> 2500 | E6: Dec 31 | F6: Income statement | G6: ='Expense Calculator'!G7 -> 2600
A7: Dec 31 | B7: Balance c/d (owing) | C7: ='Expense Calculator'!E7 -> 300 | E7: Dec 31 | F7: Balance c/d (prepaid) | G7: ='Expense Calculator'!F7 -> 0
C8: =SUM(C5:C7) -> 2800 | G8: =SUM(G5:G7) -> 2800
A9: Jan 1 | B9: Balance b/d (prepaid) | C9: ='Expense Calculator'!F7 -> 0 | E9: Jan 1 | F9: Balance b/d (owing) | G9: ='Expense Calculator'!E7 -> 300
A11: Both totals must agree. The Income statement figure is the balancing figure.

Sheet Practice
A1: Practice: Accruals and prepayments
A2: Type your answers in the yellow cells. The Check column marks them.
A3: Use the data below.
A5: Model Question 11.11 (Zara, year ended 31 March 2026)
A6: Wages owing at 1 April 2025 | B6: 300
A7: Wages paid during the year | B7: 18000
A8: Wages owing at 31 March 2026 | B8: 450
A9: Rates prepaid at 1 April 2025 | B9: 200
A10: Rates paid during the year | B10: 1600
A11: Rates prepaid at 31 March 2026 | B11: 250
A12: Commission received during the year | B12: 3000
A13: Commission still due at 31 March 2026 | B13: 250
A14: Model Question 11.7
A15: Insurance paid on 1 October 2025 for 12 months | B15: 4800
A16: Months in the year to 31 December 2025 | B16: 3
A18: Question | B18: Your answer | C18: Check
A19: Model Question 11.11
A20: Wages expense for the SPL | C20: =IF(B20="","",IFERROR(IF(ABS(B20-Answers!B20)<0.5,"Correct","Try again"),"Enter a number"))
A21: Rates expense for the SPL | C21: =IF(B21="","",IFERROR(IF(ABS(B21-Answers!B21)<0.5,"Correct","Try again"),"Enter a number"))
A22: Commission receivable for the SPL | C22: =IF(B22="","",IFERROR(IF(ABS(B22-Answers!B22)<0.5,"Correct","Try again"),"Enter a number"))
A23: Wages account: total of each side | C23: =IF(B23="","",IFERROR(IF(ABS(B23-Answers!B23)<0.5,"Correct","Try again"),"Enter a number"))
A24: SFP: total other receivables | C24: =IF(B24="","",IFERROR(IF(ABS(B24-Answers!B24)<0.5,"Correct","Try again"),"Enter a number"))
A25: SFP: total other payables | C25: =IF(B25="","",IFERROR(IF(ABS(B25-Answers!B25)<0.5,"Correct","Try again"),"Enter a number"))
A26: Model Question 11.7
A27: Insurance expense for 2025 | C27: =IF(B27="","",IFERROR(IF(ABS(B27-Answers!B27)<0.5,"Correct","Try again"),"Enter a number"))
A28: Insurance prepaid at 31 December 2025 | C28: =IF(B28="","",IFERROR(IF(ABS(B28-Answers!B28)<0.5,"Correct","Try again"),"Enter a number"))
A30: Your score (number correct) | B30: =COUNTIF(C19:C29,"Correct")&" / "&COUNTA(B19:B29)&" answered" -> 0 / 0 answered

Sheet Answers
A1: Practice: Accruals and prepayments: Answers
A2: Every answer is a formula linked to the Practice sheet data.
A18: Question | B18: Answer
A19: Model Question 11.11
A20: Wages expense for the SPL | B20: =Practice!$B$7-Practice!$B$6+Practice!$B$8 -> 18150
A21: Rates expense for the SPL | B21: =Practice!$B$10+Practice!$B$9-Practice!$B$11 -> 1550
A22: Commission receivable for the SPL | B22: =Practice!$B$12+Practice!$B$13 -> 3250
A23: Wages account: total of each side | B23: =Practice!$B$7+Practice!$B$8 -> 18450
A24: SFP: total other receivables | B24: =Practice!$B$11+Practice!$B$13 -> 500
A25: SFP: total other payables | B25: =Practice!$B$8 -> 450
A26: Model Question 11.7
A27: Insurance expense for 2025 | B27: =Practice!$B$15/12*Practice!$B$16 -> 1200
A28: Insurance prepaid at 31 December 2025 | B28: =Practice!$B$15-Practice!$B$15/12*Practice!$B$16 -> 3600
