Workbook

Sheet Read Me
A1: Chapter 12: Fundamental Accounting Principles and Concepts
A2: Senior 1 Accounting. Free to use and share.
B4: How to use this workbook
B5: 1. Start with the worked example sheets. Change any blue number and watch every answer update.
B6: 2. Then try the Practice sheet. Type your answers in the yellow cells.
B7: 3. The Check column tells you 'Correct' or 'Try again' as soon as you type.
B8: 4. The Answers sheet is hidden. When you finish, right-click any sheet tab and choose Unhide to see full answers.
B10: Colour key
B11: Blue text = an input you can change.
B12: Black text = a formula. Do not type over it.
B13: Yellow cell = your answer goes here.
B15: The Quiz sheet uses drop-down lists. Click a yellow cell and pick a concept.

Sheet Concepts
A1: The ten accounting concepts
A3: Concept | B3: Meaning | C3: Example
A4: Business entity | B4: The business is separate from its owner. | C4: Owner's private house is not recorded; goods taken are drawings.
A5: Duality | B5: Every transaction has two equal effects: a debit and a credit. | C5: Buy equipment by cheque: equipment up, bank down.
A6: Money measurement | B6: Only record items with a money value. | C6: Staff skill and customer loyalty are not recorded.
A7: Historical cost | B7: Record assets at their original cost. | C7: Land bought for $50,000 stays at $50,000.
A8: Going concern | B8: Assume the business will continue trading. | C8: Assets at cost less depreciation, not closing-down value.
A9: Realisation | B9: Record revenue when it is earned (goods pass to customer). | C9: Credit sale on 28 Dec is this year's revenue.
A10: Accruals | B10: Match income and expenses to the period they belong to. | C10: Accrued electricity; depreciation.
A11: Consistency | B11: Use the same methods every year. | C11: Keep the same depreciation method.
A12: Prudence | B12: Do not overstate assets or profit. | C12: Allowance for irrecoverable debts; inventory at lower of cost and NRV.
A13: Materiality | B13: Small items can be treated simply. | C13: A $5 stapler is an expense, not a non-current asset.
A15: Qualities of useful information
A16: Relevance | B16: Helps users make decisions; available in time.
A17: Reliability | B17: Free from errors and bias; can be checked.
A18: Comparability | B18: Can be compared with other years and businesses.
A19: Understandability | B19: Clear to users with reasonable knowledge.

Sheet NRV Calculator
A1: Inventory: lower of cost and net realisable value (prudence)
A4: Cost of goods | B4: 800
A5: Expected selling price | B5: 700
A6: Costs to sell (repairs, selling costs) | B6: 50
A8: Net realisable value (NRV) | B8: =B5-B6 -> 650
A9: Value for inventory (lower of cost and NRV) | B9: =MIN(B4,B8) -> 650

Sheet Lists
A1: Business entity
A2: Duality
A3: Money measurement
A4: Historical cost
A5: Going concern
A6: Realisation
A7: Accruals
A8: Consistency
A9: Prudence
A10: Materiality

Sheet Quiz
A1: Quiz: Which concept applies?
A2: Type your answers in the yellow cells. The Check column marks them.
A3: Choose from the drop-down list in each yellow cell.
A6: Question | B6: Your answer | C6: Check
A7: Pick the concept for each situation
A8: 12.1 The owner's private car is not in the business accounts. | C8: =IF(B8="","",IF(LOWER(TRIM(B8))=LOWER(Answers!B8),"Correct","Try again"))
A9: 12.2 Land is recorded at the price paid, not its current value. | C9: =IF(B9="","",IF(LOWER(TRIM(B9))=LOWER(Answers!B9),"Correct","Try again"))
A10: 12.3 The same depreciation method is used every year. | C10: =IF(B10="","",IF(LOWER(TRIM(B10))=LOWER(Answers!B10),"Correct","Try again"))
A11: 12.4 A $5 calculator is recorded as an expense. | C11: =IF(B11="","",IF(LOWER(TRIM(B11))=LOWER(Answers!B11),"Correct","Try again"))
A12: 12.5 Revenue is recorded when goods are delivered. | C12: =IF(B12="","",IF(LOWER(TRIM(B12))=LOWER(Answers!B12),"Correct","Try again"))
A13: 12.6 Staff skill is not recorded in the accounts. | C13: =IF(B13="","",IF(LOWER(TRIM(B13))=LOWER(Answers!B13),"Correct","Try again"))
A14: 12.7 Every transaction has a debit and a credit. | C14: =IF(B14="","",IF(LOWER(TRIM(B14))=LOWER(Answers!B14),"Correct","Try again"))
A15: 12.8 Assets shown at cost less depreciation, not closing-down prices. | C15: =IF(B15="","",IF(LOWER(TRIM(B15))=LOWER(Answers!B15),"Correct","Try again"))
A16: 12.9 December electricity paid in January is December's expense. | C16: =IF(B16="","",IF(LOWER(TRIM(B16))=LOWER(Answers!B16),"Correct","Try again"))
A17: 12.10 An allowance for irrecoverable debts is created. | C17: =IF(B17="","",IF(LOWER(TRIM(B17))=LOWER(Answers!B17),"Correct","Try again"))
A18: Extra: Inventory is valued at the lower of cost and NRV. | C18: =IF(B18="","",IF(LOWER(TRIM(B18))=LOWER(Answers!B18),"Correct","Try again"))
A19: Extra: Goods taken by the owner are recorded as drawings. | C19: =IF(B19="","",IF(LOWER(TRIM(B19))=LOWER(Answers!B19),"Correct","Try again"))
... A22: Extra: Equipment $5,000 by cheque: equipment up, bank down. | C22: =IF(B22="","",IF(LOWER(TRIM(B22))=LOWER(Answers!B22),"Correct","Try again"))
A24: Your score (number correct) | B24: =COUNTIF(C7:C23,"Correct")&" / "&COUNTA(B7:B23)&" answered" -> 0 / 0 answered

Sheet Answers
A1: Quiz: Which concept applies?: Answers
A2: Every answer is a formula linked to the Practice sheet data.
A6: Question | B6: Answer
A7: Pick the concept for each situation
A8: 12.1 The owner's private car is not in the business accounts. | B8: ="Business entity" -> Business entity
A9: 12.2 Land is recorded at the price paid, not its current value. | B9: ="Historical cost" -> Historical cost
A10: 12.3 The same depreciation method is used every year. | B10: ="Consistency" -> Consistency
A11: 12.4 A $5 calculator is recorded as an expense. | B11: ="Materiality" -> Materiality
A12: 12.5 Revenue is recorded when goods are delivered. | B12: ="Realisation" -> Realisation
A13: 12.6 Staff skill is not recorded in the accounts. | B13: ="Money measurement" -> Money measurement
A14: 12.7 Every transaction has a debit and a credit. | B14: ="Duality" -> Duality
A15: 12.8 Assets shown at cost less depreciation, not closing-down prices. | B15: ="Going concern" -> Going concern
A16: 12.9 December electricity paid in January is December's expense. | B16: ="Accruals" -> Accruals
A17: 12.10 An allowance for irrecoverable debts is created. | B17: ="Prudence" -> Prudence
A18: Extra: Inventory is valued at the lower of cost and NRV. | B18: ="Prudence" -> Prudence
A19: Extra: Goods taken by the owner are recorded as drawings. | B19: ="Business entity" -> Business entity
A20: Extra: A credit sale on 30 Dec, paid 10 Jan, is this year's revenue. | B20: ="Realisation" -> Realisation
A21: Extra: Insurance prepaid is deducted from this year's expense. | B21: ="Accruals" -> Accruals
A22: Extra: Equipment $5,000 by cheque: equipment up, bank down. | B22: ="Duality" -> Duality
